{
  "name": "Đò đưa quan họ",
  "filename": "Đò đưa quan họ.musicxml.xml",
  "processedDate": "2025-09-25T05:23:29.827Z",
  "region": "Traditional",
  "difficulty": "Intermediate",
  "noteCount": 218,
  "uniqueNotes": 8,
  "hasLyrics": true,
  "tempo": 120,
  "timeSignature": "2/4",
  "strings": 5,
  "measures": 81,
  "pitchRange": "A3-G5",
  "tuning": [
    "G4",
    "D4",
    "E4",
    "A4",
    "G3"
  ],
  "bentNotes": [
    "A3",
    "B4",
    "D5"
  ],
  "tuningSystem": "detected",
  "patternEfficiency": {
    "learnOnly": 84,
    "totalNotes": 212,
    "efficiency": 67,
    "patternCount": 338
  }
}