{
  "songTitle": "Hò đối đáp",
  "totalSyllables": 167,
  "segmentedBy": "Automatic (punctuation-based)",
  "segmentationDate": "2025-09-30",
  "phrases": [
    {
      "id": 1,
      "text": "Hơ ớ",
      "syllableCount": 2,
      "type": "narrative",
      "linguisticType": "narrative",
      "english": "",
      "wordMapping": [
        {
          "vn": "Hơ",
          "en": ""
        },
        {
          "vn": "ớ",
          "en": ""
        }
      ]
    },
    {
      "id": 2,
      "text": "Duyên cắc cớ (ớ) Tình cờ anh lại gặp",
      "syllableCount": 9,
      "type": "narrative",
      "linguisticType": "narrative",
      "english": "",
      "wordMapping": [
        {
          "vn": "Duyên",
          "en": ""
        },
        {
          "vn": "cắc",
          "en": ""
        },
        {
          "vn": "cớ",
          "en": ""
        },
        {
          "vn": "(ớ)",
          "en": ""
        },
        {
          "vn": "Tình",
          "en": ""
        },
        {
          "vn": "cờ",
          "en": ""
        },
        {
          "vn": "anh",
          "en": ""
        },
        {
          "vn": "lại",
          "en": ""
        },
        {
          "vn": "gặp",
          "en": ""
        }
      ]
    },
    {
      "id": 3,
      "text": "Này anh ôi nợ oan ương nó dồn dập nó theo hoài ơ",
      "syllableCount": 13,
      "type": "narrative",
      "linguisticType": "narrative",
      "english": "",
      "wordMapping": [
        {
          "vn": "Này",
          "en": ""
        },
        {
          "vn": "anh",
          "en": ""
        },
        {
          "vn": "ôi",
          "en": ""
        },
        {
          "vn": "nợ",
          "en": ""
        },
        {
          "vn": "oan",
          "en": ""
        },
        {
          "vn": "ương",
          "en": ""
        },
        {
          "vn": "nó",
          "en": ""
        },
        {
          "vn": "dồn",
          "en": ""
        },
        {
          "vn": "dập",
          "en": ""
        },
        {
          "vn": "nó",
          "en": ""
        },
        {
          "vn": "theo",
          "en": ""
        },
        {
          "vn": "hoài",
          "en": ""
        },
        {
          "vn": "ơ",
          "en": ""
        }
      ]
    },
    {
      "id": 4,
      "text": "ơ",
      "syllableCount": 1,
      "type": "narrative",
      "linguisticType": "narrative",
      "english": "",
      "wordMapping": [
        {
          "vn": "ơ",
          "en": ""
        }
      ]
    },
    {
      "id": 5,
      "text": "(Chào bạn lang lắng tai nghe ta hòa ớ Ớ",
      "syllableCount": 10,
      "type": "onomatopoeia",
      "linguisticType": "onomatopoeia",
      "english": "",
      "wordMapping": [
        {
          "vn": "(Chào",
          "en": ""
        },
        {
          "vn": "bạn",
          "en": ""
        },
        {
          "vn": "lang",
          "en": ""
        },
        {
          "vn": "lắng",
          "en": ""
        },
        {
          "vn": "tai",
          "en": ""
        },
        {
          "vn": "nghe",
          "en": ""
        },
        {
          "vn": "ta",
          "en": ""
        },
        {
          "vn": "hòa",
          "en": ""
        },
        {
          "vn": "ớ",
          "en": ""
        },
        {
          "vn": "Ớ",
          "en": ""
        }
      ]
    },
    {
      "id": 6,
      "text": "ơ",
      "syllableCount": 1,
      "type": "narrative",
      "linguisticType": "narrative",
      "english": "",
      "wordMapping": [
        {
          "vn": "ơ",
          "en": ""
        }
      ]
    },
    {
      "id": 7,
      "text": "ớ",
      "syllableCount": 1,
      "type": "narrative",
      "linguisticType": "narrative",
      "english": "",
      "wordMapping": [
        {
          "vn": "ớ",
          "en": ""
        }
      ]
    },
    {
      "id": 8,
      "text": "Này anh ơi",
      "syllableCount": 3,
      "type": "exclamatory",
      "linguisticType": "exclamatory",
      "english": "",
      "wordMapping": [
        {
          "vn": "Này",
          "en": ""
        },
        {
          "vn": "anh",
          "en": ""
        },
        {
          "vn": "ơi",
          "en": ""
        }
      ]
    },
    {
      "id": 9,
      "text": "chữ lương duyên của ai mà anh vô đây anh gà nghĩa",
      "syllableCount": 12,
      "type": "narrative",
      "linguisticType": "narrative",
      "english": "",
      "wordMapping": [
        {
          "vn": "chữ",
          "en": ""
        },
        {
          "vn": "lương",
          "en": ""
        },
        {
          "vn": "duyên",
          "en": ""
        },
        {
          "vn": "của",
          "en": ""
        },
        {
          "vn": "ai",
          "en": ""
        },
        {
          "vn": "mà",
          "en": ""
        },
        {
          "vn": "anh",
          "en": ""
        },
        {
          "vn": "vô",
          "en": ""
        },
        {
          "vn": "đây",
          "en": ""
        },
        {
          "vn": "anh",
          "en": ""
        },
        {
          "vn": "gà",
          "en": ""
        },
        {
          "vn": "nghĩa",
          "en": ""
        }
      ]
    },
    {
      "id": 10,
      "text": "ơ",
      "syllableCount": 1,
      "type": "narrative",
      "linguisticType": "narrative",
      "english": "",
      "wordMapping": [
        {
          "vn": "ơ",
          "en": ""
        }
      ]
    },
    {
      "id": 11,
      "text": "ơ",
      "syllableCount": 1,
      "type": "narrative",
      "linguisticType": "narrative",
      "english": "",
      "wordMapping": [
        {
          "vn": "ơ",
          "en": ""
        }
      ]
    },
    {
      "id": 12,
      "text": "ơ",
      "syllableCount": 1,
      "type": "narrative",
      "linguisticType": "narrative",
      "english": "",
      "wordMapping": [
        {
          "vn": "ơ",
          "en": ""
        }
      ]
    },
    {
      "id": 13,
      "text": "(Chào bạn lang toan bảy toan hò xê xang",
      "syllableCount": 9,
      "type": "onomatopoeia",
      "linguisticType": "onomatopoeia",
      "english": "",
      "wordMapping": [
        {
          "vn": "(Chào",
          "en": ""
        },
        {
          "vn": "bạn",
          "en": ""
        },
        {
          "vn": "lang",
          "en": ""
        },
        {
          "vn": "toan",
          "en": ""
        },
        {
          "vn": "bảy",
          "en": ""
        },
        {
          "vn": "toan",
          "en": ""
        },
        {
          "vn": "hò",
          "en": ""
        },
        {
          "vn": "xê",
          "en": ""
        },
        {
          "vn": "xang",
          "en": ""
        }
      ]
    },
    {
      "id": 14,
      "text": "hò",
      "syllableCount": 1,
      "type": "onomatopoeia",
      "linguisticType": "onomatopoeia",
      "english": "",
      "wordMapping": [
        {
          "vn": "hò",
          "en": ""
        }
      ]
    },
    {
      "id": 15,
      "text": "ơ",
      "syllableCount": 1,
      "type": "narrative",
      "linguisticType": "narrative",
      "english": "",
      "wordMapping": [
        {
          "vn": "ơ",
          "en": ""
        }
      ]
    },
    {
      "id": 16,
      "text": "mà tôi sợ ông trời đầy (ơ) cái kiếp mà sau (Quân tử tồn hò sự cống hò ơ ơ",
      "syllableCount": 20,
      "type": "onomatopoeia",
      "linguisticType": "onomatopoeia",
      "english": "",
      "wordMapping": [
        {
          "vn": "mà",
          "en": ""
        },
        {
          "vn": "tôi",
          "en": ""
        },
        {
          "vn": "sợ",
          "en": ""
        },
        {
          "vn": "ông",
          "en": ""
        },
        {
          "vn": "trời",
          "en": ""
        },
        {
          "vn": "đầy",
          "en": ""
        },
        {
          "vn": "(ơ)",
          "en": ""
        },
        {
          "vn": "cái",
          "en": ""
        },
        {
          "vn": "kiếp",
          "en": ""
        },
        {
          "vn": "mà",
          "en": ""
        },
        {
          "vn": "sau",
          "en": ""
        },
        {
          "vn": "(Quân",
          "en": ""
        },
        {
          "vn": "tử",
          "en": ""
        },
        {
          "vn": "tồn",
          "en": ""
        },
        {
          "vn": "hò",
          "en": ""
        },
        {
          "vn": "sự",
          "en": ""
        },
        {
          "vn": "cống",
          "en": ""
        },
        {
          "vn": "hò",
          "en": ""
        },
        {
          "vn": "ơ",
          "en": ""
        },
        {
          "vn": "ơ",
          "en": ""
        }
      ]
    },
    {
      "id": 17,
      "text": "Nhạn lạc bầy khó gầy duyên oanh én",
      "syllableCount": 8,
      "type": "narrative",
      "linguisticType": "narrative",
      "english": "",
      "wordMapping": [
        {
          "vn": "Nhạn",
          "en": ""
        },
        {
          "vn": "lạc",
          "en": ""
        },
        {
          "vn": "bầy",
          "en": ""
        },
        {
          "vn": "khó",
          "en": ""
        },
        {
          "vn": "gầy",
          "en": ""
        },
        {
          "vn": "duyên",
          "en": ""
        },
        {
          "vn": "oanh",
          "en": ""
        },
        {
          "vn": "én",
          "en": ""
        }
      ]
    },
    {
      "id": 18,
      "text": "em ơi nghĩa vợ tình chồng thì núp lẻn yêu nhau ơ",
      "syllableCount": 12,
      "type": "exclamatory",
      "linguisticType": "exclamatory",
      "english": "",
      "wordMapping": [
        {
          "vn": "em",
          "en": ""
        },
        {
          "vn": "ơi",
          "en": ""
        },
        {
          "vn": "nghĩa",
          "en": ""
        },
        {
          "vn": "vợ",
          "en": ""
        },
        {
          "vn": "tình",
          "en": ""
        },
        {
          "vn": "chồng",
          "en": ""
        },
        {
          "vn": "thì",
          "en": ""
        },
        {
          "vn": "núp",
          "en": ""
        },
        {
          "vn": "lẻn",
          "en": ""
        },
        {
          "vn": "yêu",
          "en": ""
        },
        {
          "vn": "nhau",
          "en": ""
        },
        {
          "vn": "ơ",
          "en": ""
        }
      ]
    },
    {
      "id": 19,
      "text": "ơ (Chào bạn lang lắng tai nghe ta Hò",
      "syllableCount": 9,
      "type": "narrative",
      "linguisticType": "narrative",
      "english": "",
      "wordMapping": [
        {
          "vn": "ơ",
          "en": ""
        },
        {
          "vn": "(Chào",
          "en": ""
        },
        {
          "vn": "bạn",
          "en": ""
        },
        {
          "vn": "lang",
          "en": ""
        },
        {
          "vn": "lắng",
          "en": ""
        },
        {
          "vn": "tai",
          "en": ""
        },
        {
          "vn": "nghe",
          "en": ""
        },
        {
          "vn": "ta",
          "en": ""
        },
        {
          "vn": "Hò",
          "en": ""
        }
      ]
    },
    {
      "id": 20,
      "text": "ơ",
      "syllableCount": 1,
      "type": "narrative",
      "linguisticType": "narrative",
      "english": "",
      "wordMapping": [
        {
          "vn": "ơ",
          "en": ""
        }
      ]
    },
    {
      "id": 21,
      "text": "Em ơi có gặp cảnh khó nghèo sớm cháo chiều rau thì em ơi hãy vui dạ ơ ơ (Chào bạn lang toan bảy toan hò xang xế Hò ơ",
      "syllableCount": 30,
      "type": "exclamatory",
      "linguisticType": "exclamatory",
      "english": "",
      "wordMapping": [
        {
          "vn": "Em",
          "en": ""
        },
        {
          "vn": "ơi",
          "en": ""
        },
        {
          "vn": "có",
          "en": ""
        },
        {
          "vn": "gặp",
          "en": ""
        },
        {
          "vn": "cảnh",
          "en": ""
        },
        {
          "vn": "khó",
          "en": ""
        },
        {
          "vn": "nghèo",
          "en": ""
        },
        {
          "vn": "sớm",
          "en": ""
        },
        {
          "vn": "cháo",
          "en": ""
        },
        {
          "vn": "chiều",
          "en": ""
        },
        {
          "vn": "rau",
          "en": ""
        },
        {
          "vn": "thì",
          "en": ""
        },
        {
          "vn": "em",
          "en": ""
        },
        {
          "vn": "ơi",
          "en": ""
        },
        {
          "vn": "hãy",
          "en": ""
        },
        {
          "vn": "vui",
          "en": ""
        },
        {
          "vn": "dạ",
          "en": ""
        },
        {
          "vn": "ơ",
          "en": ""
        },
        {
          "vn": "ơ",
          "en": ""
        },
        {
          "vn": "(Chào",
          "en": ""
        },
        {
          "vn": "bạn",
          "en": ""
        },
        {
          "vn": "lang",
          "en": ""
        },
        {
          "vn": "toan",
          "en": ""
        },
        {
          "vn": "bảy",
          "en": ""
        },
        {
          "vn": "toan",
          "en": ""
        },
        {
          "vn": "hò",
          "en": ""
        },
        {
          "vn": "xang",
          "en": ""
        },
        {
          "vn": "xế",
          "en": ""
        },
        {
          "vn": "Hò",
          "en": ""
        },
        {
          "vn": "ơ",
          "en": ""
        }
      ]
    },
    {
      "id": 22,
      "text": "ơ ơ",
      "syllableCount": 2,
      "type": "narrative",
      "linguisticType": "narrative",
      "english": "",
      "wordMapping": [
        {
          "vn": "ơ",
          "en": ""
        },
        {
          "vn": "ơ",
          "en": ""
        }
      ]
    },
    {
      "id": 23,
      "text": "Chớ anh có biết liệu làm (ơ) sao hỡi mình ơ (Quân ơ",
      "syllableCount": 13,
      "type": "narrative",
      "linguisticType": "narrative",
      "english": "",
      "wordMapping": [
        {
          "vn": "Chớ",
          "en": ""
        },
        {
          "vn": "anh",
          "en": ""
        },
        {
          "vn": "có",
          "en": ""
        },
        {
          "vn": "biết",
          "en": ""
        },
        {
          "vn": "liệu",
          "en": ""
        },
        {
          "vn": "làm",
          "en": ""
        },
        {
          "vn": "(ơ)",
          "en": ""
        },
        {
          "vn": "sao",
          "en": ""
        },
        {
          "vn": "hỡi",
          "en": ""
        },
        {
          "vn": "mình",
          "en": ""
        },
        {
          "vn": "ơ",
          "en": ""
        },
        {
          "vn": "(Quân",
          "en": ""
        },
        {
          "vn": "ơ",
          "en": ""
        }
      ]
    },
    {
      "id": 24,
      "text": "tử tồn hò xự cống xê)",
      "syllableCount": 6,
      "type": "onomatopoeia",
      "linguisticType": "onomatopoeia",
      "english": "",
      "wordMapping": [
        {
          "vn": "tử",
          "en": ""
        },
        {
          "vn": "tồn",
          "en": ""
        },
        {
          "vn": "hò",
          "en": ""
        },
        {
          "vn": "xự",
          "en": ""
        },
        {
          "vn": "cống",
          "en": ""
        },
        {
          "vn": "xê)",
          "en": ""
        }
      ]
    }
  ],
  "statistics": {
    "totalSyllables": 167,
    "totalPhrases": 24,
    "averagePhraseLength": "6.96"
  }
}