{
  "songTitle": "Hát ru Thùa thiên - Huế",
  "totalSyllables": 36,
  "segmentedBy": "Automatic (punctuation-based)",
  "segmentationDate": "2025-09-30",
  "phrases": [
    {
      "id": 1,
      "text": "À a ơi Em ơi",
      "syllableCount": 5,
      "type": "exclamatory",
      "linguisticType": "exclamatory",
      "english": "",
      "wordMapping": [
        {
          "vn": "À",
          "en": ""
        },
        {
          "vn": "a",
          "en": ""
        },
        {
          "vn": "ơi",
          "en": ""
        },
        {
          "vn": "Em",
          "en": ""
        },
        {
          "vn": "ơi",
          "en": ""
        }
      ],
      "culturalContext": {
        "description": "This phrase features \"Em\" - younger person or term of endearment. The exclamatory form adds emotional emphasis, common in Vietnamese folk music to engage listeners.",
        "facts": [
          "Vietnamese folk songs preserve oral traditions passed down through generations without written notation",
          "Dan Tranh (16-string zither) arrangements of folk songs are relatively modern adaptations of vocal traditions",
          "Many folk songs use nature imagery to express human emotions indirectly",
          "The pentatonic scale used in Vietnamese folk music creates a distinctively Asian sound palette"
        ],
        "musicalContext": "This exclamatory phrase contains 5 syllables, slightly longer than the typical 4-syllable pattern, adding emphasis or conclusion. As an exclamatory phrase, it likely features sustained notes or ascending contours for emotional expression."
      }
    },
    {
      "id": 2,
      "text": "em ơi em ngủ cho muồi Để mẹ đi chợ (mà) mua vôi ăn À a ơi",
      "syllableCount": 17,
      "type": "exclamatory",
      "linguisticType": "exclamatory",
      "english": "",
      "wordMapping": [
        {
          "vn": "em",
          "en": ""
        },
        {
          "vn": "ơi",
          "en": ""
        },
        {
          "vn": "em",
          "en": ""
        },
        {
          "vn": "ngủ",
          "en": ""
        },
        {
          "vn": "cho",
          "en": ""
        },
        {
          "vn": "muồi",
          "en": ""
        },
        {
          "vn": "Để",
          "en": ""
        },
        {
          "vn": "mẹ",
          "en": ""
        },
        {
          "vn": "đi",
          "en": ""
        },
        {
          "vn": "chợ",
          "en": ""
        },
        {
          "vn": "(mà)",
          "en": ""
        },
        {
          "vn": "mua",
          "en": ""
        },
        {
          "vn": "vôi",
          "en": ""
        },
        {
          "vn": "ăn",
          "en": ""
        },
        {
          "vn": "À",
          "en": ""
        },
        {
          "vn": "a",
          "en": ""
        },
        {
          "vn": "ơi",
          "en": ""
        }
      ],
      "culturalContext": {
        "description": "This phrase features \"Em\" - younger person or term of endearment. The exclamatory form adds emotional emphasis, common in Vietnamese folk music to engage listeners.",
        "facts": [
          "Vietnamese folk songs preserve oral traditions passed down through generations without written notation",
          "Dan Tranh (16-string zither) arrangements of folk songs are relatively modern adaptations of vocal traditions",
          "Many folk songs use nature imagery to express human emotions indirectly",
          "The pentatonic scale used in Vietnamese folk music creates a distinctively Asian sound palette"
        ],
        "musicalContext": "This exclamatory phrase contains 17 syllables, longer than typical, allowing for extended melodic development. As an exclamatory phrase, it likely features sustained notes or ascending contours for emotional expression."
      }
    },
    {
      "id": 3,
      "text": "Mua vôi chợ Quán chợ Cầu Mua cau Nam Phổ",
      "syllableCount": 10,
      "type": "narrative",
      "linguisticType": "narrative",
      "english": "",
      "wordMapping": [
        {
          "vn": "Mua",
          "en": ""
        },
        {
          "vn": "vôi",
          "en": ""
        },
        {
          "vn": "chợ",
          "en": ""
        },
        {
          "vn": "Quán",
          "en": ""
        },
        {
          "vn": "chợ",
          "en": ""
        },
        {
          "vn": "Cầu",
          "en": ""
        },
        {
          "vn": "Mua",
          "en": ""
        },
        {
          "vn": "cau",
          "en": ""
        },
        {
          "vn": "Nam",
          "en": ""
        },
        {
          "vn": "Phổ",
          "en": ""
        }
      ],
      "culturalContext": {
        "description": "This narrative phrase advances the story, grounding the emotional content in concrete imagery.",
        "facts": [
          "Vietnamese folk songs preserve oral traditions passed down through generations without written notation",
          "Dan Tranh (16-string zither) arrangements of folk songs are relatively modern adaptations of vocal traditions",
          "Many folk songs use nature imagery to express human emotions indirectly",
          "The pentatonic scale used in Vietnamese folk music creates a distinctively Asian sound palette"
        ],
        "musicalContext": "This narrative phrase contains 10 syllables, longer than typical, allowing for extended melodic development. Narrative phrases typically use moderate melodic range and steady rhythm to advance the story."
      }
    },
    {
      "id": 4,
      "text": "mua trầu chợ Dinh",
      "syllableCount": 4,
      "type": "narrative",
      "linguisticType": "narrative",
      "english": "",
      "wordMapping": [
        {
          "vn": "mua",
          "en": ""
        },
        {
          "vn": "trầu",
          "en": ""
        },
        {
          "vn": "chợ",
          "en": ""
        },
        {
          "vn": "Dinh",
          "en": ""
        }
      ],
      "culturalContext": {
        "description": "This narrative phrase advances the story, grounding the emotional content in concrete imagery.",
        "facts": [
          "Vietnamese folk songs preserve oral traditions passed down through generations without written notation",
          "Dan Tranh (16-string zither) arrangements of folk songs are relatively modern adaptations of vocal traditions",
          "Many folk songs use nature imagery to express human emotions indirectly",
          "The pentatonic scale used in Vietnamese folk music creates a distinctively Asian sound palette"
        ],
        "musicalContext": "This narrative phrase contains 4 syllables, the most common phrase length in Vietnamese folk music, creating balanced musical phrasing. Narrative phrases typically use moderate melodic range and steady rhythm to advance the story."
      }
    }
  ],
  "statistics": {
    "totalSyllables": 36,
    "totalPhrases": 4,
    "averagePhraseLength": "9.00"
  }
}