{
  "songTitle": "Cặp bù kè",
  "totalSyllables": 16,
  "segmentedBy": "Automatic (punctuation-based)",
  "segmentationDate": "2025-09-30",
  "phrases": [
    {
      "id": 1,
      "text": "Cặp bù kè chấm muối mè",
      "syllableCount": 6,
      "type": "narrative",
      "linguisticType": "narrative",
      "english": "",
      "wordMapping": [
        {
          "vn": "Cặp",
          "en": ""
        },
        {
          "vn": "bù",
          "en": ""
        },
        {
          "vn": "kè",
          "en": ""
        },
        {
          "vn": "chấm",
          "en": ""
        },
        {
          "vn": "muối",
          "en": ""
        },
        {
          "vn": "mè",
          "en": ""
        }
      ],
      "culturalContext": {
        "description": "This narrative phrase advances the story, grounding the emotional content in concrete imagery.",
        "facts": [
          "Vietnamese folk songs preserve oral traditions passed down through generations without written notation",
          "Dan Tranh (16-string zither) arrangements of folk songs are relatively modern adaptations of vocal traditions",
          "Many folk songs use nature imagery to express human emotions indirectly",
          "The pentatonic scale used in Vietnamese folk music creates a distinctively Asian sound palette"
        ],
        "musicalContext": "This narrative phrase contains 6 syllables, longer than typical, allowing for extended melodic development. Narrative phrases typically use moderate melodic range and steady rhythm to advance the story."
      }
    },
    {
      "id": 2,
      "text": "Ăn với xôi ăn bình vôi phỏng miệng",
      "syllableCount": 8,
      "type": "narrative",
      "linguisticType": "narrative",
      "english": "",
      "wordMapping": [
        {
          "vn": "Ăn",
          "en": ""
        },
        {
          "vn": "với",
          "en": ""
        },
        {
          "vn": "xôi",
          "en": ""
        },
        {
          "vn": "ăn",
          "en": ""
        },
        {
          "vn": "bình",
          "en": ""
        },
        {
          "vn": "vôi",
          "en": ""
        },
        {
          "vn": "phỏng",
          "en": ""
        },
        {
          "vn": "miệng",
          "en": ""
        }
      ],
      "culturalContext": {
        "description": "This narrative phrase advances the story, grounding the emotional content in concrete imagery.",
        "facts": [
          "Vietnamese folk songs preserve oral traditions passed down through generations without written notation",
          "Dan Tranh (16-string zither) arrangements of folk songs are relatively modern adaptations of vocal traditions",
          "Many folk songs use nature imagery to express human emotions indirectly",
          "The pentatonic scale used in Vietnamese folk music creates a distinctively Asian sound palette"
        ],
        "musicalContext": "This narrative phrase contains 8 syllables, longer than typical, allowing for extended melodic development. Narrative phrases typically use moderate melodic range and steady rhythm to advance the story."
      }
    },
    {
      "id": 3,
      "text": "Ngồi xuống",
      "syllableCount": 2,
      "type": "narrative",
      "linguisticType": "narrative",
      "english": "",
      "wordMapping": [
        {
          "vn": "Ngồi",
          "en": ""
        },
        {
          "vn": "xuống",
          "en": ""
        }
      ],
      "culturalContext": {
        "description": "This narrative phrase advances the story, grounding the emotional content in concrete imagery.",
        "facts": [
          "Vietnamese folk songs preserve oral traditions passed down through generations without written notation",
          "Dan Tranh (16-string zither) arrangements of folk songs are relatively modern adaptations of vocal traditions",
          "Many folk songs use nature imagery to express human emotions indirectly",
          "The pentatonic scale used in Vietnamese folk music creates a distinctively Asian sound palette"
        ],
        "musicalContext": "This narrative phrase contains 2 syllables. Narrative phrases typically use moderate melodic range and steady rhythm to advance the story."
      }
    }
  ],
  "statistics": {
    "totalSyllables": 16,
    "totalPhrases": 3,
    "averagePhraseLength": "5.33"
  }
}