{
  "metadata": {
    "songName": "Lý con cua",
    "totalNotes": 59,
    "mainNotes": 56,
    "graceNotes": 3,
    "totalSyllables": 42,
    "melismaCount": 14,
    "generatedDate": "2025-10-12T14:22:12.523Z",
    "taxonomyVersion": "4.4.8",
    "migrationDate": "2025-10-16T20:04:10.698Z"
  },
  "wordToNoteMap": [
    {
      "phraseId": 1,
      "wordIndex": 0,
      "syllable": "Con",
      "tone": "ngang",
      "rhymeFamily": "on",
      "translation": "The crab",
      "noteIds": [
        "note_0"
      ],
      "mainNoteId": "note_0",
      "hasGraceNotes": false,
      "graceNotesBefore": [],
      "graceNotesAfter": [],
      "isMelisma": false,
      "melismaNotes": [],
      "structuralRole": "verse",
      "structuralPosition": "opening",
      "linguisticType": "narrative",
      "semanticCategory": "abstract"
    },
    {
      "phraseId": 1,
      "wordIndex": 1,
      "syllable": "cua",
      "tone": "ngang",
      "rhymeFamily": "a",
      "translation": "The crab",
      "noteIds": [
        "note_1",
        "note_2"
      ],
      "mainNoteId": "note_1",
      "hasGraceNotes": false,
      "graceNotesBefore": [],
      "graceNotesAfter": [],
      "isMelisma": true,
      "melismaNotes": [
        "note_2"
      ],
      "structuralRole": "verse",
      "structuralPosition": "opening",
      "linguisticType": "narrative",
      "semanticCategory": "abstract"
    },
    {
      "phraseId": 1,
      "wordIndex": 2,
      "syllable": "quẫy",
      "tone": "ngã",
      "rhymeFamily": "i",
      "translation": "thrashes/flails",
      "noteIds": [
        "note_3"
      ],
      "mainNoteId": "note_3",
      "hasGraceNotes": false,
      "graceNotesBefore": [],
      "graceNotesAfter": [],
      "isMelisma": false,
      "melismaNotes": [],
      "structuralRole": "verse",
      "structuralPosition": "opening",
      "linguisticType": "narrative",
      "semanticCategory": "abstract"
    },
    {
      "phraseId": 1,
      "wordIndex": 3,
      "syllable": "nó",
      "tone": "sắc",
      "rhymeFamily": "o",
      "translation": "it",
      "noteIds": [
        "note_4"
      ],
      "mainNoteId": "note_4",
      "hasGraceNotes": false,
      "graceNotesBefore": [],
      "graceNotesAfter": [],
      "isMelisma": false,
      "melismaNotes": [],
      "structuralRole": "verse",
      "structuralPosition": "opening",
      "linguisticType": "narrative",
      "semanticCategory": "abstract"
    },
    {
      "phraseId": 1,
      "wordIndex": 4,
      "syllable": "ở",
      "tone": "hỏi",
      "rhymeFamily": "ơ",
      "translation": "in/at",
      "noteIds": [
        "note_5",
        "note_6"
      ],
      "mainNoteId": "note_5",
      "hasGraceNotes": false,
      "graceNotesBefore": [],
      "graceNotesAfter": [],
      "isMelisma": true,
      "melismaNotes": [
        "note_6"
      ],
      "structuralRole": "verse",
      "structuralPosition": "opening",
      "linguisticType": "narrative",
      "semanticCategory": "abstract"
    },
    {
      "phraseId": 1,
      "wordIndex": 5,
      "syllable": "trong",
      "tone": "ngang",
      "rhymeFamily": "ong",
      "translation": "inside",
      "noteIds": [
        "note_7"
      ],
      "mainNoteId": "note_7",
      "hasGraceNotes": false,
      "graceNotesBefore": [],
      "graceNotesAfter": [],
      "isMelisma": false,
      "melismaNotes": [],
      "structuralRole": "verse",
      "structuralPosition": "opening",
      "linguisticType": "narrative",
      "semanticCategory": "abstract"
    },
    {
      "phraseId": 1,
      "wordIndex": 6,
      "syllable": "hang",
      "tone": "ngang",
      "rhymeFamily": "ang",
      "translation": "cave/burrow",
      "noteIds": [
        "note_8"
      ],
      "mainNoteId": "note_8",
      "hasGraceNotes": false,
      "graceNotesBefore": [],
      "graceNotesAfter": [],
      "isMelisma": false,
      "melismaNotes": [],
      "structuralRole": "verse",
      "structuralPosition": "opening",
      "linguisticType": "narrative",
      "semanticCategory": "abstract"
    },
    {
      "phraseId": 2,
      "wordIndex": 7,
      "syllable": "quẫy",
      "tone": "ngã",
      "rhymeFamily": "i",
      "translation": "thrashing",
      "noteIds": [
        "note_9",
        "note_10"
      ],
      "mainNoteId": "note_9",
      "hasGraceNotes": false,
      "graceNotesBefore": [],
      "graceNotesAfter": [],
      "isMelisma": true,
      "melismaNotes": [
        "note_10"
      ],
      "structuralRole": "refrain",
      "structuralPosition": "middle",
      "linguisticType": "narrative",
      "semanticCategory": "abstract"
    },
    {
      "phraseId": 2,
      "wordIndex": 8,
      "syllable": "a",
      "tone": "ngang",
      "rhymeFamily": "a",
      "translation": "ah",
      "noteIds": [
        "note_11",
        "note_12"
      ],
      "mainNoteId": "note_11",
      "hasGraceNotes": false,
      "graceNotesBefore": [],
      "graceNotesAfter": [],
      "isMelisma": true,
      "melismaNotes": [
        "note_12"
      ],
      "structuralRole": "refrain",
      "structuralPosition": "middle",
      "linguisticType": "narrative",
      "semanticCategory": "abstract"
    },
    {
      "phraseId": 2,
      "wordIndex": 9,
      "syllable": "rượng",
      "tone": "nặng",
      "rhymeFamily": "ương",
      "translation": "tumbling",
      "noteIds": [
        "note_13"
      ],
      "mainNoteId": "note_13",
      "hasGraceNotes": false,
      "graceNotesBefore": [],
      "graceNotesAfter": [],
      "isMelisma": false,
      "melismaNotes": [],
      "structuralRole": "refrain",
      "structuralPosition": "middle",
      "linguisticType": "narrative",
      "semanticCategory": "abstract"
    },
    {
      "phraseId": 2,
      "wordIndex": 10,
      "syllable": "a.",
      "tone": "ngang",
      "rhymeFamily": "other",
      "translation": "ah",
      "noteIds": [
        "note_14"
      ],
      "mainNoteId": "note_14",
      "hasGraceNotes": false,
      "graceNotesBefore": [],
      "graceNotesAfter": [],
      "isMelisma": false,
      "melismaNotes": [],
      "structuralRole": "refrain",
      "structuralPosition": "middle",
      "linguisticType": "narrative",
      "semanticCategory": "abstract"
    },
    {
      "phraseId": 3,
      "wordIndex": 11,
      "syllable": "Nó",
      "tone": "sắc",
      "rhymeFamily": "o",
      "translation": "It cries/calls",
      "noteIds": [
        "note_15"
      ],
      "mainNoteId": "note_15",
      "hasGraceNotes": false,
      "graceNotesBefore": [],
      "graceNotesAfter": [],
      "isMelisma": false,
      "melismaNotes": [],
      "structuralRole": "verse",
      "structuralPosition": "middle",
      "linguisticType": "narrative",
      "semanticCategory": "abstract"
    },
    {
      "phraseId": 3,
      "wordIndex": 12,
      "syllable": "kêu",
      "tone": "ngang",
      "rhymeFamily": "u",
      "translation": "It cries/calls",
      "noteIds": [
        "note_16"
      ],
      "mainNoteId": "note_16",
      "hasGraceNotes": false,
      "graceNotesBefore": [],
      "graceNotesAfter": [],
      "isMelisma": false,
      "melismaNotes": [],
      "structuralRole": "verse",
      "structuralPosition": "middle",
      "linguisticType": "narrative",
      "semanticCategory": "abstract"
    },
    {
      "phraseId": 3,
      "wordIndex": 13,
      "syllable": "ớ",
      "tone": "sắc",
      "rhymeFamily": "ơ",
      "translation": "onomatopoetic sounds",
      "noteIds": [
        "note_17",
        "note_18"
      ],
      "mainNoteId": "note_18",
      "hasGraceNotes": true,
      "graceNotesBefore": [
        "note_17"
      ],
      "graceNotesAfter": [],
      "isMelisma": false,
      "melismaNotes": [],
      "structuralRole": "verse",
      "structuralPosition": "middle",
      "linguisticType": "narrative",
      "semanticCategory": "abstract"
    },
    {
      "phraseId": 3,
      "wordIndex": 14,
      "syllable": "rịnh",
      "tone": "nặng",
      "rhymeFamily": "inh",
      "translation": "onomatopoetic sounds",
      "noteIds": [
        "note_19",
        "note_20"
      ],
      "mainNoteId": "note_19",
      "hasGraceNotes": false,
      "graceNotesBefore": [],
      "graceNotesAfter": [],
      "isMelisma": true,
      "melismaNotes": [
        "note_20"
      ],
      "structuralRole": "verse",
      "structuralPosition": "middle",
      "linguisticType": "narrative",
      "semanticCategory": "abstract"
    },
    {
      "phraseId": 3,
      "wordIndex": 15,
      "syllable": "boong",
      "tone": "ngang",
      "rhymeFamily": "ong",
      "translation": "onomatopoetic sounds",
      "noteIds": [
        "note_21"
      ],
      "mainNoteId": "note_21",
      "hasGraceNotes": false,
      "graceNotesBefore": [],
      "graceNotesAfter": [],
      "isMelisma": false,
      "melismaNotes": [],
      "structuralRole": "verse",
      "structuralPosition": "middle",
      "linguisticType": "narrative",
      "semanticCategory": "abstract"
    },
    {
      "phraseId": 3,
      "wordIndex": 16,
      "syllable": "rinh",
      "tone": "ngang",
      "rhymeFamily": "inh",
      "translation": "onomatopoetic sounds",
      "noteIds": [
        "note_22"
      ],
      "mainNoteId": "note_22",
      "hasGraceNotes": false,
      "graceNotesBefore": [],
      "graceNotesAfter": [],
      "isMelisma": false,
      "melismaNotes": [],
      "structuralRole": "verse",
      "structuralPosition": "middle",
      "linguisticType": "narrative",
      "semanticCategory": "abstract"
    },
    {
      "phraseId": 3,
      "wordIndex": 17,
      "syllable": "ớ",
      "tone": "sắc",
      "rhymeFamily": "ơ",
      "translation": "onomatopoetic sounds",
      "noteIds": [
        "note_23",
        "note_24"
      ],
      "mainNoteId": "note_24",
      "hasGraceNotes": true,
      "graceNotesBefore": [
        "note_23"
      ],
      "graceNotesAfter": [],
      "isMelisma": false,
      "melismaNotes": [],
      "structuralRole": "verse",
      "structuralPosition": "middle",
      "linguisticType": "narrative",
      "semanticCategory": "abstract"
    },
    {
      "phraseId": 3,
      "wordIndex": 18,
      "syllable": "rịnh",
      "tone": "nặng",
      "rhymeFamily": "inh",
      "translation": "onomatopoetic sounds",
      "noteIds": [
        "note_25",
        "note_26"
      ],
      "mainNoteId": "note_25",
      "hasGraceNotes": false,
      "graceNotesBefore": [],
      "graceNotesAfter": [],
      "isMelisma": true,
      "melismaNotes": [
        "note_26"
      ],
      "structuralRole": "verse",
      "structuralPosition": "middle",
      "linguisticType": "narrative",
      "semanticCategory": "abstract"
    },
    {
      "phraseId": 3,
      "wordIndex": 19,
      "syllable": "boong",
      "tone": "ngang",
      "rhymeFamily": "ong",
      "translation": "onomatopoetic sounds",
      "noteIds": [
        "note_27"
      ],
      "mainNoteId": "note_27",
      "hasGraceNotes": false,
      "graceNotesBefore": [],
      "graceNotesAfter": [],
      "isMelisma": false,
      "melismaNotes": [],
      "structuralRole": "verse",
      "structuralPosition": "middle",
      "linguisticType": "narrative",
      "semanticCategory": "abstract"
    },
    {
      "phraseId": 3,
      "wordIndex": 20,
      "syllable": "ơi",
      "tone": "ngang",
      "rhymeFamily": "i",
      "translation": "onomatopoetic sounds",
      "noteIds": [
        "note_28"
      ],
      "mainNoteId": "note_28",
      "hasGraceNotes": false,
      "graceNotesBefore": [],
      "graceNotesAfter": [],
      "isMelisma": false,
      "melismaNotes": [],
      "structuralRole": "verse",
      "structuralPosition": "middle",
      "linguisticType": "narrative",
      "semanticCategory": "abstract"
    },
    {
      "phraseId": 4,
      "wordIndex": 21,
      "syllable": "quẫy",
      "tone": "ngã",
      "rhymeFamily": "i",
      "translation": "thrashing",
      "noteIds": [
        "note_29",
        "note_30"
      ],
      "mainNoteId": "note_29",
      "hasGraceNotes": false,
      "graceNotesBefore": [],
      "graceNotesAfter": [],
      "isMelisma": true,
      "melismaNotes": [
        "note_30"
      ],
      "structuralRole": "refrain",
      "structuralPosition": "middle",
      "linguisticType": "narrative",
      "semanticCategory": "abstract"
    },
    {
      "phraseId": 4,
      "wordIndex": 22,
      "syllable": "a",
      "tone": "ngang",
      "rhymeFamily": "a",
      "translation": "ah",
      "noteIds": [
        "note_31",
        "note_32"
      ],
      "mainNoteId": "note_31",
      "hasGraceNotes": false,
      "graceNotesBefore": [],
      "graceNotesAfter": [],
      "isMelisma": true,
      "melismaNotes": [
        "note_32"
      ],
      "structuralRole": "refrain",
      "structuralPosition": "middle",
      "linguisticType": "narrative",
      "semanticCategory": "abstract"
    },
    {
      "phraseId": 4,
      "wordIndex": 23,
      "syllable": "rượng",
      "tone": "nặng",
      "rhymeFamily": "ương",
      "translation": "tumbling",
      "noteIds": [
        "note_33"
      ],
      "mainNoteId": "note_33",
      "hasGraceNotes": false,
      "graceNotesBefore": [],
      "graceNotesAfter": [],
      "isMelisma": false,
      "melismaNotes": [],
      "structuralRole": "refrain",
      "structuralPosition": "middle",
      "linguisticType": "narrative",
      "semanticCategory": "abstract"
    },
    {
      "phraseId": 4,
      "wordIndex": 24,
      "syllable": "a.",
      "tone": "ngang",
      "rhymeFamily": "other",
      "translation": "ah",
      "noteIds": [
        "note_34"
      ],
      "mainNoteId": "note_34",
      "hasGraceNotes": false,
      "graceNotesBefore": [],
      "graceNotesAfter": [],
      "isMelisma": false,
      "melismaNotes": [],
      "structuralRole": "refrain",
      "structuralPosition": "middle",
      "linguisticType": "narrative",
      "semanticCategory": "abstract"
    },
    {
      "phraseId": 5,
      "wordIndex": 25,
      "syllable": "Lang",
      "tone": "ngang",
      "rhymeFamily": "ang",
      "translation": "rhythmic percussion sounds",
      "noteIds": [
        "note_35"
      ],
      "mainNoteId": "note_35",
      "hasGraceNotes": false,
      "graceNotesBefore": [],
      "graceNotesAfter": [],
      "isMelisma": false,
      "melismaNotes": [],
      "structuralRole": "verse",
      "structuralPosition": "middle",
      "linguisticType": "narrative",
      "semanticCategory": "spiritual"
    },
    {
      "phraseId": 5,
      "wordIndex": 26,
      "syllable": "tang",
      "tone": "ngang",
      "rhymeFamily": "ang",
      "translation": "rhythmic percussion sounds",
      "noteIds": [
        "note_36"
      ],
      "mainNoteId": "note_36",
      "hasGraceNotes": false,
      "graceNotesBefore": [],
      "graceNotesAfter": [],
      "isMelisma": false,
      "melismaNotes": [],
      "structuralRole": "verse",
      "structuralPosition": "middle",
      "linguisticType": "narrative",
      "semanticCategory": "spiritual"
    },
    {
      "phraseId": 5,
      "wordIndex": 27,
      "syllable": "tính",
      "tone": "sắc",
      "rhymeFamily": "inh",
      "translation": "rhythmic percussion sounds",
      "noteIds": [
        "note_37"
      ],
      "mainNoteId": "note_37",
      "hasGraceNotes": false,
      "graceNotesBefore": [],
      "graceNotesAfter": [],
      "isMelisma": false,
      "melismaNotes": [],
      "structuralRole": "verse",
      "structuralPosition": "middle",
      "linguisticType": "narrative",
      "semanticCategory": "spiritual"
    },
    {
      "phraseId": 5,
      "wordIndex": 28,
      "syllable": "lính",
      "tone": "sắc",
      "rhymeFamily": "inh",
      "translation": "rhythmic percussion sounds",
      "noteIds": [
        "note_38"
      ],
      "mainNoteId": "note_38",
      "hasGraceNotes": false,
      "graceNotesBefore": [],
      "graceNotesAfter": [],
      "isMelisma": false,
      "melismaNotes": [],
      "structuralRole": "verse",
      "structuralPosition": "middle",
      "linguisticType": "narrative",
      "semanticCategory": "spiritual"
    },
    {
      "phraseId": 5,
      "wordIndex": 29,
      "syllable": "tinh",
      "tone": "ngang",
      "rhymeFamily": "inh",
      "translation": "rhythmic percussion sounds",
      "noteIds": [
        "note_39"
      ],
      "mainNoteId": "note_39",
      "hasGraceNotes": false,
      "graceNotesBefore": [],
      "graceNotesAfter": [],
      "isMelisma": false,
      "melismaNotes": [],
      "structuralRole": "verse",
      "structuralPosition": "middle",
      "linguisticType": "narrative",
      "semanticCategory": "spiritual"
    },
    {
      "phraseId": 5,
      "wordIndex": 30,
      "syllable": "tang,",
      "tone": "ngang",
      "rhymeFamily": "other",
      "translation": "rhythmic percussion sounds",
      "noteIds": [
        "note_40"
      ],
      "mainNoteId": "note_40",
      "hasGraceNotes": false,
      "graceNotesBefore": [],
      "graceNotesAfter": [],
      "isMelisma": false,
      "melismaNotes": [],
      "structuralRole": "verse",
      "structuralPosition": "middle",
      "linguisticType": "narrative",
      "semanticCategory": "spiritual"
    },
    {
      "phraseId": 5,
      "wordIndex": 31,
      "syllable": "linh",
      "tone": "ngang",
      "rhymeFamily": "inh",
      "translation": "rhythmic percussion sounds",
      "noteIds": [
        "note_41",
        "note_42"
      ],
      "mainNoteId": "note_41",
      "hasGraceNotes": false,
      "graceNotesBefore": [],
      "graceNotesAfter": [],
      "isMelisma": true,
      "melismaNotes": [
        "note_42"
      ],
      "structuralRole": "verse",
      "structuralPosition": "middle",
      "linguisticType": "narrative",
      "semanticCategory": "spiritual"
    },
    {
      "phraseId": 5,
      "wordIndex": 32,
      "syllable": "tính",
      "tone": "sắc",
      "rhymeFamily": "inh",
      "translation": "rhythmic percussion sounds",
      "noteIds": [
        "note_43",
        "note_44"
      ],
      "mainNoteId": "note_43",
      "hasGraceNotes": false,
      "graceNotesBefore": [],
      "graceNotesAfter": [],
      "isMelisma": true,
      "melismaNotes": [
        "note_44"
      ],
      "structuralRole": "verse",
      "structuralPosition": "middle",
      "linguisticType": "narrative",
      "semanticCategory": "spiritual"
    },
    {
      "phraseId": 5,
      "wordIndex": 33,
      "syllable": "tang,",
      "tone": "ngang",
      "rhymeFamily": "other",
      "translation": "rhythmic percussion sounds",
      "noteIds": [
        "note_45"
      ],
      "mainNoteId": "note_45",
      "hasGraceNotes": false,
      "graceNotesBefore": [],
      "graceNotesAfter": [],
      "isMelisma": false,
      "melismaNotes": [],
      "structuralRole": "verse",
      "structuralPosition": "middle",
      "linguisticType": "narrative",
      "semanticCategory": "spiritual"
    },
    {
      "phraseId": 6,
      "wordIndex": 34,
      "syllable": "giã",
      "tone": "ngã",
      "rhymeFamily": "a",
      "translation": "pound rice",
      "noteIds": [
        "note_46",
        "note_47"
      ],
      "mainNoteId": "note_47",
      "hasGraceNotes": true,
      "graceNotesBefore": [
        "note_46"
      ],
      "graceNotesAfter": [],
      "isMelisma": false,
      "melismaNotes": [],
      "structuralRole": "verse",
      "structuralPosition": "middle",
      "linguisticType": "narrative",
      "semanticCategory": "abstract"
    },
    {
      "phraseId": 6,
      "wordIndex": 35,
      "syllable": "gạo",
      "tone": "nặng",
      "rhymeFamily": "o",
      "translation": "pound rice",
      "noteIds": [
        "note_48",
        "note_49"
      ],
      "mainNoteId": "note_48",
      "hasGraceNotes": false,
      "graceNotesBefore": [],
      "graceNotesAfter": [],
      "isMelisma": true,
      "melismaNotes": [
        "note_49"
      ],
      "structuralRole": "verse",
      "structuralPosition": "middle",
      "linguisticType": "narrative",
      "semanticCategory": "abstract"
    },
    {
      "phraseId": 6,
      "wordIndex": 36,
      "syllable": "chày",
      "tone": "huyền",
      "rhymeFamily": "i",
      "translation": "pestle",
      "noteIds": [
        "note_50",
        "note_51"
      ],
      "mainNoteId": "note_50",
      "hasGraceNotes": false,
      "graceNotesBefore": [],
      "graceNotesAfter": [],
      "isMelisma": true,
      "melismaNotes": [
        "note_51"
      ],
      "structuralRole": "verse",
      "structuralPosition": "middle",
      "linguisticType": "narrative",
      "semanticCategory": "abstract"
    },
    {
      "phraseId": 6,
      "wordIndex": 37,
      "syllable": "ba",
      "tone": "ngang",
      "rhymeFamily": "a",
      "translation": "three",
      "noteIds": [
        "note_52"
      ],
      "mainNoteId": "note_52",
      "hasGraceNotes": false,
      "graceNotesBefore": [],
      "graceNotesAfter": [],
      "isMelisma": false,
      "melismaNotes": [],
      "structuralRole": "verse",
      "structuralPosition": "middle",
      "linguisticType": "narrative",
      "semanticCategory": "abstract"
    },
    {
      "phraseId": 7,
      "wordIndex": 38,
      "syllable": "quẫy",
      "tone": "ngã",
      "rhymeFamily": "i",
      "translation": "thrashing",
      "noteIds": [
        "note_53",
        "note_54"
      ],
      "mainNoteId": "note_53",
      "hasGraceNotes": false,
      "graceNotesBefore": [],
      "graceNotesAfter": [],
      "isMelisma": true,
      "melismaNotes": [
        "note_54"
      ],
      "structuralRole": "refrain",
      "structuralPosition": "closing",
      "linguisticType": "narrative",
      "semanticCategory": "abstract"
    },
    {
      "phraseId": 7,
      "wordIndex": 39,
      "syllable": "a",
      "tone": "ngang",
      "rhymeFamily": "a",
      "translation": "ah",
      "noteIds": [
        "note_55",
        "note_56"
      ],
      "mainNoteId": "note_55",
      "hasGraceNotes": false,
      "graceNotesBefore": [],
      "graceNotesAfter": [],
      "isMelisma": true,
      "melismaNotes": [
        "note_56"
      ],
      "structuralRole": "refrain",
      "structuralPosition": "closing",
      "linguisticType": "narrative",
      "semanticCategory": "abstract"
    },
    {
      "phraseId": 7,
      "wordIndex": 40,
      "syllable": "rượng",
      "tone": "nặng",
      "rhymeFamily": "ương",
      "translation": "tumbling",
      "noteIds": [
        "note_57"
      ],
      "mainNoteId": "note_57",
      "hasGraceNotes": false,
      "graceNotesBefore": [],
      "graceNotesAfter": [],
      "isMelisma": false,
      "melismaNotes": [],
      "structuralRole": "refrain",
      "structuralPosition": "closing",
      "linguisticType": "narrative",
      "semanticCategory": "abstract"
    },
    {
      "phraseId": 7,
      "wordIndex": 41,
      "syllable": "a.",
      "tone": "ngang",
      "rhymeFamily": "other",
      "translation": "ah",
      "noteIds": [
        "note_58"
      ],
      "mainNoteId": "note_58",
      "hasGraceNotes": false,
      "graceNotesBefore": [],
      "graceNotesAfter": [],
      "isMelisma": false,
      "melismaNotes": [],
      "structuralRole": "refrain",
      "structuralPosition": "closing",
      "linguisticType": "narrative",
      "semanticCategory": "abstract"
    }
  ],
  "noteToWordMap": {
    "note_0": {
      "phraseId": 1,
      "wordIndex": 0,
      "syllable": "Con",
      "tone": "ngang",
      "rhymeFamily": "on",
      "translation": "The crab",
      "phraseType": "narrative",
      "isMainNote": true,
      "isGraceNote": false,
      "isMelismaNote": false
    },
    "note_1": {
      "phraseId": 1,
      "wordIndex": 1,
      "syllable": "cua",
      "tone": "ngang",
      "rhymeFamily": "a",
      "translation": "The crab",
      "phraseType": "narrative",
      "isMainNote": true,
      "isGraceNote": false,
      "isMelismaNote": false
    },
    "note_2": {
      "phraseId": 1,
      "wordIndex": 1,
      "syllable": "cua",
      "tone": "ngang",
      "rhymeFamily": "a",
      "translation": "The crab",
      "phraseType": "narrative",
      "isMainNote": false,
      "isGraceNote": false,
      "isMelismaNote": true
    },
    "note_3": {
      "phraseId": 1,
      "wordIndex": 2,
      "syllable": "quẫy",
      "tone": "ngã",
      "rhymeFamily": "i",
      "translation": "thrashes/flails",
      "phraseType": "narrative",
      "isMainNote": true,
      "isGraceNote": false,
      "isMelismaNote": false
    },
    "note_4": {
      "phraseId": 1,
      "wordIndex": 3,
      "syllable": "nó",
      "tone": "sắc",
      "rhymeFamily": "o",
      "translation": "it",
      "phraseType": "narrative",
      "isMainNote": true,
      "isGraceNote": false,
      "isMelismaNote": false
    },
    "note_5": {
      "phraseId": 1,
      "wordIndex": 4,
      "syllable": "ở",
      "tone": "hỏi",
      "rhymeFamily": "ơ",
      "translation": "in/at",
      "phraseType": "narrative",
      "isMainNote": true,
      "isGraceNote": false,
      "isMelismaNote": false
    },
    "note_6": {
      "phraseId": 1,
      "wordIndex": 4,
      "syllable": "ở",
      "tone": "hỏi",
      "rhymeFamily": "ơ",
      "translation": "in/at",
      "phraseType": "narrative",
      "isMainNote": false,
      "isGraceNote": false,
      "isMelismaNote": true
    },
    "note_7": {
      "phraseId": 1,
      "wordIndex": 5,
      "syllable": "trong",
      "tone": "ngang",
      "rhymeFamily": "ong",
      "translation": "inside",
      "phraseType": "narrative",
      "isMainNote": true,
      "isGraceNote": false,
      "isMelismaNote": false
    },
    "note_8": {
      "phraseId": 1,
      "wordIndex": 6,
      "syllable": "hang",
      "tone": "ngang",
      "rhymeFamily": "ang",
      "translation": "cave/burrow",
      "phraseType": "narrative",
      "isMainNote": true,
      "isGraceNote": false,
      "isMelismaNote": false
    },
    "note_9": {
      "phraseId": 2,
      "wordIndex": 7,
      "syllable": "quẫy",
      "tone": "ngã",
      "rhymeFamily": "i",
      "translation": "thrashing",
      "phraseType": "refrain",
      "isMainNote": true,
      "isGraceNote": false,
      "isMelismaNote": false
    },
    "note_10": {
      "phraseId": 2,
      "wordIndex": 7,
      "syllable": "quẫy",
      "tone": "ngã",
      "rhymeFamily": "i",
      "translation": "thrashing",
      "phraseType": "refrain",
      "isMainNote": false,
      "isGraceNote": false,
      "isMelismaNote": true
    },
    "note_11": {
      "phraseId": 2,
      "wordIndex": 8,
      "syllable": "a",
      "tone": "ngang",
      "rhymeFamily": "a",
      "translation": "ah",
      "phraseType": "refrain",
      "isMainNote": true,
      "isGraceNote": false,
      "isMelismaNote": false
    },
    "note_12": {
      "phraseId": 2,
      "wordIndex": 8,
      "syllable": "a",
      "tone": "ngang",
      "rhymeFamily": "a",
      "translation": "ah",
      "phraseType": "refrain",
      "isMainNote": false,
      "isGraceNote": false,
      "isMelismaNote": true
    },
    "note_13": {
      "phraseId": 2,
      "wordIndex": 9,
      "syllable": "rượng",
      "tone": "nặng",
      "rhymeFamily": "ương",
      "translation": "tumbling",
      "phraseType": "refrain",
      "isMainNote": true,
      "isGraceNote": false,
      "isMelismaNote": false
    },
    "note_14": {
      "phraseId": 2,
      "wordIndex": 10,
      "syllable": "a.",
      "tone": "ngang",
      "rhymeFamily": "other",
      "translation": "ah",
      "phraseType": "refrain",
      "isMainNote": true,
      "isGraceNote": false,
      "isMelismaNote": false
    },
    "note_15": {
      "phraseId": 3,
      "wordIndex": 11,
      "syllable": "Nó",
      "tone": "sắc",
      "rhymeFamily": "o",
      "translation": "It cries/calls",
      "phraseType": "onomatopoeia",
      "isMainNote": true,
      "isGraceNote": false,
      "isMelismaNote": false
    },
    "note_16": {
      "phraseId": 3,
      "wordIndex": 12,
      "syllable": "kêu",
      "tone": "ngang",
      "rhymeFamily": "u",
      "translation": "It cries/calls",
      "phraseType": "onomatopoeia",
      "isMainNote": true,
      "isGraceNote": false,
      "isMelismaNote": false
    },
    "note_17": {
      "phraseId": 3,
      "wordIndex": 13,
      "syllable": "ớ",
      "tone": "sắc",
      "rhymeFamily": "ơ",
      "translation": "onomatopoetic sounds",
      "phraseType": "onomatopoeia",
      "isMainNote": false,
      "isGraceNote": true,
      "isMelismaNote": false
    },
    "note_18": {
      "phraseId": 3,
      "wordIndex": 13,
      "syllable": "ớ",
      "tone": "sắc",
      "rhymeFamily": "ơ",
      "translation": "onomatopoetic sounds",
      "phraseType": "onomatopoeia",
      "isMainNote": true,
      "isGraceNote": false,
      "isMelismaNote": false
    },
    "note_19": {
      "phraseId": 3,
      "wordIndex": 14,
      "syllable": "rịnh",
      "tone": "nặng",
      "rhymeFamily": "inh",
      "translation": "onomatopoetic sounds",
      "phraseType": "onomatopoeia",
      "isMainNote": true,
      "isGraceNote": false,
      "isMelismaNote": false
    },
    "note_20": {
      "phraseId": 3,
      "wordIndex": 14,
      "syllable": "rịnh",
      "tone": "nặng",
      "rhymeFamily": "inh",
      "translation": "onomatopoetic sounds",
      "phraseType": "onomatopoeia",
      "isMainNote": false,
      "isGraceNote": false,
      "isMelismaNote": true
    },
    "note_21": {
      "phraseId": 3,
      "wordIndex": 15,
      "syllable": "boong",
      "tone": "ngang",
      "rhymeFamily": "ong",
      "translation": "onomatopoetic sounds",
      "phraseType": "onomatopoeia",
      "isMainNote": true,
      "isGraceNote": false,
      "isMelismaNote": false
    },
    "note_22": {
      "phraseId": 3,
      "wordIndex": 16,
      "syllable": "rinh",
      "tone": "ngang",
      "rhymeFamily": "inh",
      "translation": "onomatopoetic sounds",
      "phraseType": "onomatopoeia",
      "isMainNote": true,
      "isGraceNote": false,
      "isMelismaNote": false
    },
    "note_23": {
      "phraseId": 3,
      "wordIndex": 17,
      "syllable": "ớ",
      "tone": "sắc",
      "rhymeFamily": "ơ",
      "translation": "onomatopoetic sounds",
      "phraseType": "onomatopoeia",
      "isMainNote": false,
      "isGraceNote": true,
      "isMelismaNote": false
    },
    "note_24": {
      "phraseId": 3,
      "wordIndex": 17,
      "syllable": "ớ",
      "tone": "sắc",
      "rhymeFamily": "ơ",
      "translation": "onomatopoetic sounds",
      "phraseType": "onomatopoeia",
      "isMainNote": true,
      "isGraceNote": false,
      "isMelismaNote": false
    },
    "note_25": {
      "phraseId": 3,
      "wordIndex": 18,
      "syllable": "rịnh",
      "tone": "nặng",
      "rhymeFamily": "inh",
      "translation": "onomatopoetic sounds",
      "phraseType": "onomatopoeia",
      "isMainNote": true,
      "isGraceNote": false,
      "isMelismaNote": false
    },
    "note_26": {
      "phraseId": 3,
      "wordIndex": 18,
      "syllable": "rịnh",
      "tone": "nặng",
      "rhymeFamily": "inh",
      "translation": "onomatopoetic sounds",
      "phraseType": "onomatopoeia",
      "isMainNote": false,
      "isGraceNote": false,
      "isMelismaNote": true
    },
    "note_27": {
      "phraseId": 3,
      "wordIndex": 19,
      "syllable": "boong",
      "tone": "ngang",
      "rhymeFamily": "ong",
      "translation": "onomatopoetic sounds",
      "phraseType": "onomatopoeia",
      "isMainNote": true,
      "isGraceNote": false,
      "isMelismaNote": false
    },
    "note_28": {
      "phraseId": 3,
      "wordIndex": 20,
      "syllable": "ơi",
      "tone": "ngang",
      "rhymeFamily": "i",
      "translation": "onomatopoetic sounds",
      "phraseType": "onomatopoeia",
      "isMainNote": true,
      "isGraceNote": false,
      "isMelismaNote": false
    },
    "note_29": {
      "phraseId": 4,
      "wordIndex": 21,
      "syllable": "quẫy",
      "tone": "ngã",
      "rhymeFamily": "i",
      "translation": "thrashing",
      "phraseType": "refrain",
      "isMainNote": true,
      "isGraceNote": false,
      "isMelismaNote": false
    },
    "note_30": {
      "phraseId": 4,
      "wordIndex": 21,
      "syllable": "quẫy",
      "tone": "ngã",
      "rhymeFamily": "i",
      "translation": "thrashing",
      "phraseType": "refrain",
      "isMainNote": false,
      "isGraceNote": false,
      "isMelismaNote": true
    },
    "note_31": {
      "phraseId": 4,
      "wordIndex": 22,
      "syllable": "a",
      "tone": "ngang",
      "rhymeFamily": "a",
      "translation": "ah",
      "phraseType": "refrain",
      "isMainNote": true,
      "isGraceNote": false,
      "isMelismaNote": false
    },
    "note_32": {
      "phraseId": 4,
      "wordIndex": 22,
      "syllable": "a",
      "tone": "ngang",
      "rhymeFamily": "a",
      "translation": "ah",
      "phraseType": "refrain",
      "isMainNote": false,
      "isGraceNote": false,
      "isMelismaNote": true
    },
    "note_33": {
      "phraseId": 4,
      "wordIndex": 23,
      "syllable": "rượng",
      "tone": "nặng",
      "rhymeFamily": "ương",
      "translation": "tumbling",
      "phraseType": "refrain",
      "isMainNote": true,
      "isGraceNote": false,
      "isMelismaNote": false
    },
    "note_34": {
      "phraseId": 4,
      "wordIndex": 24,
      "syllable": "a.",
      "tone": "ngang",
      "rhymeFamily": "other",
      "translation": "ah",
      "phraseType": "refrain",
      "isMainNote": true,
      "isGraceNote": false,
      "isMelismaNote": false
    },
    "note_35": {
      "phraseId": 5,
      "wordIndex": 25,
      "syllable": "Lang",
      "tone": "ngang",
      "rhymeFamily": "ang",
      "translation": "rhythmic percussion sounds",
      "phraseType": "onomatopoeia",
      "isMainNote": true,
      "isGraceNote": false,
      "isMelismaNote": false
    },
    "note_36": {
      "phraseId": 5,
      "wordIndex": 26,
      "syllable": "tang",
      "tone": "ngang",
      "rhymeFamily": "ang",
      "translation": "rhythmic percussion sounds",
      "phraseType": "onomatopoeia",
      "isMainNote": true,
      "isGraceNote": false,
      "isMelismaNote": false
    },
    "note_37": {
      "phraseId": 5,
      "wordIndex": 27,
      "syllable": "tính",
      "tone": "sắc",
      "rhymeFamily": "inh",
      "translation": "rhythmic percussion sounds",
      "phraseType": "onomatopoeia",
      "isMainNote": true,
      "isGraceNote": false,
      "isMelismaNote": false
    },
    "note_38": {
      "phraseId": 5,
      "wordIndex": 28,
      "syllable": "lính",
      "tone": "sắc",
      "rhymeFamily": "inh",
      "translation": "rhythmic percussion sounds",
      "phraseType": "onomatopoeia",
      "isMainNote": true,
      "isGraceNote": false,
      "isMelismaNote": false
    },
    "note_39": {
      "phraseId": 5,
      "wordIndex": 29,
      "syllable": "tinh",
      "tone": "ngang",
      "rhymeFamily": "inh",
      "translation": "rhythmic percussion sounds",
      "phraseType": "onomatopoeia",
      "isMainNote": true,
      "isGraceNote": false,
      "isMelismaNote": false
    },
    "note_40": {
      "phraseId": 5,
      "wordIndex": 30,
      "syllable": "tang,",
      "tone": "ngang",
      "rhymeFamily": "other",
      "translation": "rhythmic percussion sounds",
      "phraseType": "onomatopoeia",
      "isMainNote": true,
      "isGraceNote": false,
      "isMelismaNote": false
    },
    "note_41": {
      "phraseId": 5,
      "wordIndex": 31,
      "syllable": "linh",
      "tone": "ngang",
      "rhymeFamily": "inh",
      "translation": "rhythmic percussion sounds",
      "phraseType": "onomatopoeia",
      "isMainNote": true,
      "isGraceNote": false,
      "isMelismaNote": false
    },
    "note_42": {
      "phraseId": 5,
      "wordIndex": 31,
      "syllable": "linh",
      "tone": "ngang",
      "rhymeFamily": "inh",
      "translation": "rhythmic percussion sounds",
      "phraseType": "onomatopoeia",
      "isMainNote": false,
      "isGraceNote": false,
      "isMelismaNote": true
    },
    "note_43": {
      "phraseId": 5,
      "wordIndex": 32,
      "syllable": "tính",
      "tone": "sắc",
      "rhymeFamily": "inh",
      "translation": "rhythmic percussion sounds",
      "phraseType": "onomatopoeia",
      "isMainNote": true,
      "isGraceNote": false,
      "isMelismaNote": false
    },
    "note_44": {
      "phraseId": 5,
      "wordIndex": 32,
      "syllable": "tính",
      "tone": "sắc",
      "rhymeFamily": "inh",
      "translation": "rhythmic percussion sounds",
      "phraseType": "onomatopoeia",
      "isMainNote": false,
      "isGraceNote": false,
      "isMelismaNote": true
    },
    "note_45": {
      "phraseId": 5,
      "wordIndex": 33,
      "syllable": "tang,",
      "tone": "ngang",
      "rhymeFamily": "other",
      "translation": "rhythmic percussion sounds",
      "phraseType": "onomatopoeia",
      "isMainNote": true,
      "isGraceNote": false,
      "isMelismaNote": false
    },
    "note_46": {
      "phraseId": 6,
      "wordIndex": 34,
      "syllable": "giã",
      "tone": "ngã",
      "rhymeFamily": "a",
      "translation": "pound rice",
      "phraseType": "narrative",
      "isMainNote": false,
      "isGraceNote": true,
      "isMelismaNote": false
    },
    "note_47": {
      "phraseId": 6,
      "wordIndex": 34,
      "syllable": "giã",
      "tone": "ngã",
      "rhymeFamily": "a",
      "translation": "pound rice",
      "phraseType": "narrative",
      "isMainNote": true,
      "isGraceNote": false,
      "isMelismaNote": false
    },
    "note_48": {
      "phraseId": 6,
      "wordIndex": 35,
      "syllable": "gạo",
      "tone": "nặng",
      "rhymeFamily": "o",
      "translation": "pound rice",
      "phraseType": "narrative",
      "isMainNote": true,
      "isGraceNote": false,
      "isMelismaNote": false
    },
    "note_49": {
      "phraseId": 6,
      "wordIndex": 35,
      "syllable": "gạo",
      "tone": "nặng",
      "rhymeFamily": "o",
      "translation": "pound rice",
      "phraseType": "narrative",
      "isMainNote": false,
      "isGraceNote": false,
      "isMelismaNote": true
    },
    "note_50": {
      "phraseId": 6,
      "wordIndex": 36,
      "syllable": "chày",
      "tone": "huyền",
      "rhymeFamily": "i",
      "translation": "pestle",
      "phraseType": "narrative",
      "isMainNote": true,
      "isGraceNote": false,
      "isMelismaNote": false
    },
    "note_51": {
      "phraseId": 6,
      "wordIndex": 36,
      "syllable": "chày",
      "tone": "huyền",
      "rhymeFamily": "i",
      "translation": "pestle",
      "phraseType": "narrative",
      "isMainNote": false,
      "isGraceNote": false,
      "isMelismaNote": true
    },
    "note_52": {
      "phraseId": 6,
      "wordIndex": 37,
      "syllable": "ba",
      "tone": "ngang",
      "rhymeFamily": "a",
      "translation": "three",
      "phraseType": "narrative",
      "isMainNote": true,
      "isGraceNote": false,
      "isMelismaNote": false
    },
    "note_53": {
      "phraseId": 7,
      "wordIndex": 38,
      "syllable": "quẫy",
      "tone": "ngã",
      "rhymeFamily": "i",
      "translation": "thrashing",
      "phraseType": "refrain",
      "isMainNote": true,
      "isGraceNote": false,
      "isMelismaNote": false
    },
    "note_54": {
      "phraseId": 7,
      "wordIndex": 38,
      "syllable": "quẫy",
      "tone": "ngã",
      "rhymeFamily": "i",
      "translation": "thrashing",
      "phraseType": "refrain",
      "isMainNote": false,
      "isGraceNote": false,
      "isMelismaNote": true
    },
    "note_55": {
      "phraseId": 7,
      "wordIndex": 39,
      "syllable": "a",
      "tone": "ngang",
      "rhymeFamily": "a",
      "translation": "ah",
      "phraseType": "refrain",
      "isMainNote": true,
      "isGraceNote": false,
      "isMelismaNote": false
    },
    "note_56": {
      "phraseId": 7,
      "wordIndex": 39,
      "syllable": "a",
      "tone": "ngang",
      "rhymeFamily": "a",
      "translation": "ah",
      "phraseType": "refrain",
      "isMainNote": false,
      "isGraceNote": false,
      "isMelismaNote": true
    },
    "note_57": {
      "phraseId": 7,
      "wordIndex": 40,
      "syllable": "rượng",
      "tone": "nặng",
      "rhymeFamily": "ương",
      "translation": "tumbling",
      "phraseType": "refrain",
      "isMainNote": true,
      "isGraceNote": false,
      "isMelismaNote": false
    },
    "note_58": {
      "phraseId": 7,
      "wordIndex": 41,
      "syllable": "a.",
      "tone": "ngang",
      "rhymeFamily": "other",
      "translation": "ah",
      "phraseType": "refrain",
      "isMainNote": true,
      "isGraceNote": false,
      "isMelismaNote": false
    }
  },
  "notes": [
    {
      "id": "note_0",
      "index": 0,
      "measureNumber": 1,
      "pitch": "D5",
      "duration": 4,
      "isGrace": false,
      "lyrics": "Con",
      "hasTieStart": false,
      "hasTieStop": false,
      "hasSlurStart": false,
      "hasSlurStop": false
    },
    {
      "id": "note_1",
      "index": 1,
      "measureNumber": 1,
      "pitch": "D5",
      "duration": 2,
      "isGrace": false,
      "lyrics": "cua",
      "hasTieStart": false,
      "hasTieStop": false,
      "hasSlurStart": true,
      "hasSlurStop": false
    },
    {
      "id": "note_2",
      "index": 2,
      "measureNumber": 1,
      "pitch": "C5",
      "duration": 2,
      "isGrace": false,
      "lyrics": null,
      "hasTieStart": false,
      "hasTieStop": false,
      "hasSlurStart": false,
      "hasSlurStop": true
    },
    {
      "id": "note_3",
      "index": 3,
      "measureNumber": 2,
      "pitch": "A4",
      "duration": 4,
      "isGrace": false,
      "lyrics": "quẫy",
      "hasTieStart": false,
      "hasTieStop": false,
      "hasSlurStart": false,
      "hasSlurStop": false
    },
    {
      "id": "note_4",
      "index": 4,
      "measureNumber": 2,
      "pitch": "F5",
      "duration": 2,
      "isGrace": false,
      "lyrics": "nó",
      "hasTieStart": false,
      "hasTieStop": false,
      "hasSlurStart": false,
      "hasSlurStop": false
    },
    {
      "id": "note_5",
      "index": 5,
      "measureNumber": 3,
      "pitch": "A4",
      "duration": 2,
      "isGrace": false,
      "lyrics": "ở",
      "hasTieStart": false,
      "hasTieStop": false,
      "hasSlurStart": true,
      "hasSlurStop": false
    },
    {
      "id": "note_6",
      "index": 6,
      "measureNumber": 3,
      "pitch": "F5",
      "duration": 2,
      "isGrace": false,
      "lyrics": null,
      "hasTieStart": false,
      "hasTieStop": false,
      "hasSlurStart": false,
      "hasSlurStop": true
    },
    {
      "id": "note_7",
      "index": 7,
      "measureNumber": 3,
      "pitch": "D5",
      "duration": 4,
      "isGrace": false,
      "lyrics": "trong",
      "hasTieStart": false,
      "hasTieStop": false,
      "hasSlurStart": false,
      "hasSlurStop": false
    },
    {
      "id": "note_8",
      "index": 8,
      "measureNumber": 4,
      "pitch": "D5",
      "duration": 4,
      "isGrace": false,
      "lyrics": "hang",
      "hasTieStart": false,
      "hasTieStop": false,
      "hasSlurStart": false,
      "hasSlurStop": false
    },
    {
      "id": "note_9",
      "index": 9,
      "measureNumber": 4,
      "pitch": "D5",
      "duration": 2,
      "isGrace": false,
      "lyrics": "quẫy",
      "hasTieStart": false,
      "hasTieStop": false,
      "hasSlurStart": true,
      "hasSlurStop": false
    },
    {
      "id": "note_10",
      "index": 10,
      "measureNumber": 4,
      "pitch": "F5",
      "duration": 2,
      "isGrace": false,
      "lyrics": null,
      "hasTieStart": false,
      "hasTieStop": false,
      "hasSlurStart": false,
      "hasSlurStop": true
    },
    {
      "id": "note_11",
      "index": 11,
      "measureNumber": 5,
      "pitch": "D5",
      "duration": 2,
      "isGrace": false,
      "lyrics": "a",
      "hasTieStart": false,
      "hasTieStop": false,
      "hasSlurStart": true,
      "hasSlurStop": false
    },
    {
      "id": "note_12",
      "index": 12,
      "measureNumber": 5,
      "pitch": "C5",
      "duration": 2,
      "isGrace": false,
      "lyrics": null,
      "hasTieStart": false,
      "hasTieStop": false,
      "hasSlurStart": false,
      "hasSlurStop": true
    },
    {
      "id": "note_13",
      "index": 13,
      "measureNumber": 5,
      "pitch": "A4",
      "duration": 4,
      "isGrace": false,
      "lyrics": "rượng",
      "hasTieStart": false,
      "hasTieStop": false,
      "hasSlurStart": false,
      "hasSlurStop": false
    },
    {
      "id": "note_14",
      "index": 14,
      "measureNumber": 6,
      "pitch": "C5",
      "duration": 4,
      "isGrace": false,
      "lyrics": "a.",
      "hasTieStart": false,
      "hasTieStop": false,
      "hasSlurStart": false,
      "hasSlurStop": false
    },
    {
      "id": "note_15",
      "index": 15,
      "measureNumber": 6,
      "pitch": "F5",
      "duration": 2,
      "isGrace": false,
      "lyrics": "Nó",
      "hasTieStart": false,
      "hasTieStop": false,
      "hasSlurStart": false,
      "hasSlurStop": false
    },
    {
      "id": "note_16",
      "index": 16,
      "measureNumber": 7,
      "pitch": "D5",
      "duration": 4,
      "isGrace": false,
      "lyrics": "kêu",
      "hasTieStart": false,
      "hasTieStop": false,
      "hasSlurStart": false,
      "hasSlurStop": false
    },
    {
      "id": "note_17",
      "index": 17,
      "measureNumber": 7,
      "pitch": "D5",
      "duration": 0,
      "isGrace": true,
      "lyrics": null,
      "hasTieStart": false,
      "hasTieStop": false,
      "hasSlurStart": true,
      "hasSlurStop": false
    },
    {
      "id": "note_18",
      "index": 18,
      "measureNumber": 7,
      "pitch": "F5",
      "duration": 2,
      "isGrace": false,
      "lyrics": "ớ",
      "hasTieStart": false,
      "hasTieStop": false,
      "hasSlurStart": false,
      "hasSlurStop": true
    },
    {
      "id": "note_19",
      "index": 19,
      "measureNumber": 8,
      "pitch": "A4",
      "duration": 2,
      "isGrace": false,
      "lyrics": "rịnh",
      "hasTieStart": false,
      "hasTieStop": false,
      "hasSlurStart": true,
      "hasSlurStop": false
    },
    {
      "id": "note_20",
      "index": 20,
      "measureNumber": 8,
      "pitch": "C5",
      "duration": 2,
      "isGrace": false,
      "lyrics": null,
      "hasTieStart": false,
      "hasTieStop": false,
      "hasSlurStart": false,
      "hasSlurStop": true
    },
    {
      "id": "note_21",
      "index": 21,
      "measureNumber": 8,
      "pitch": "A4",
      "duration": 4,
      "isGrace": false,
      "lyrics": "boong",
      "hasTieStart": false,
      "hasTieStop": false,
      "hasSlurStart": false,
      "hasSlurStop": false
    },
    {
      "id": "note_22",
      "index": 22,
      "measureNumber": 9,
      "pitch": "A4",
      "duration": 4,
      "isGrace": false,
      "lyrics": "rinh",
      "hasTieStart": false,
      "hasTieStop": false,
      "hasSlurStart": false,
      "hasSlurStop": false
    },
    {
      "id": "note_23",
      "index": 23,
      "measureNumber": 9,
      "pitch": "D5",
      "duration": 0,
      "isGrace": true,
      "lyrics": null,
      "hasTieStart": false,
      "hasTieStop": false,
      "hasSlurStart": true,
      "hasSlurStop": false
    },
    {
      "id": "note_24",
      "index": 24,
      "measureNumber": 9,
      "pitch": "F5",
      "duration": 2,
      "isGrace": false,
      "lyrics": "ớ",
      "hasTieStart": false,
      "hasTieStop": false,
      "hasSlurStart": false,
      "hasSlurStop": true
    },
    {
      "id": "note_25",
      "index": 25,
      "measureNumber": 10,
      "pitch": "A4",
      "duration": 2,
      "isGrace": false,
      "lyrics": "rịnh",
      "hasTieStart": false,
      "hasTieStop": false,
      "hasSlurStart": true,
      "hasSlurStop": false
    },
    {
      "id": "note_26",
      "index": 26,
      "measureNumber": 10,
      "pitch": "C5",
      "duration": 2,
      "isGrace": false,
      "lyrics": null,
      "hasTieStart": false,
      "hasTieStop": false,
      "hasSlurStart": false,
      "hasSlurStop": true
    },
    {
      "id": "note_27",
      "index": 27,
      "measureNumber": 10,
      "pitch": "A4",
      "duration": 4,
      "isGrace": false,
      "lyrics": "boong",
      "hasTieStart": false,
      "hasTieStop": false,
      "hasSlurStart": false,
      "hasSlurStop": false
    },
    {
      "id": "note_28",
      "index": 28,
      "measureNumber": 11,
      "pitch": "D5",
      "duration": 4,
      "isGrace": false,
      "lyrics": "ơi",
      "hasTieStart": false,
      "hasTieStop": false,
      "hasSlurStart": false,
      "hasSlurStop": false
    },
    {
      "id": "note_29",
      "index": 29,
      "measureNumber": 11,
      "pitch": "D5",
      "duration": 2,
      "isGrace": false,
      "lyrics": "quẫy",
      "hasTieStart": false,
      "hasTieStop": false,
      "hasSlurStart": true,
      "hasSlurStop": false
    },
    {
      "id": "note_30",
      "index": 30,
      "measureNumber": 11,
      "pitch": "F5",
      "duration": 2,
      "isGrace": false,
      "lyrics": null,
      "hasTieStart": false,
      "hasTieStop": false,
      "hasSlurStart": false,
      "hasSlurStop": true
    },
    {
      "id": "note_31",
      "index": 31,
      "measureNumber": 12,
      "pitch": "D5",
      "duration": 2,
      "isGrace": false,
      "lyrics": "a",
      "hasTieStart": false,
      "hasTieStop": false,
      "hasSlurStart": true,
      "hasSlurStop": false
    },
    {
      "id": "note_32",
      "index": 32,
      "measureNumber": 12,
      "pitch": "C5",
      "duration": 2,
      "isGrace": false,
      "lyrics": null,
      "hasTieStart": false,
      "hasTieStop": false,
      "hasSlurStart": false,
      "hasSlurStop": true
    },
    {
      "id": "note_33",
      "index": 33,
      "measureNumber": 12,
      "pitch": "A4",
      "duration": 4,
      "isGrace": false,
      "lyrics": "rượng",
      "hasTieStart": false,
      "hasTieStop": false,
      "hasSlurStart": false,
      "hasSlurStop": false
    },
    {
      "id": "note_34",
      "index": 34,
      "measureNumber": 13,
      "pitch": "C5",
      "duration": 2,
      "isGrace": false,
      "lyrics": "a.",
      "hasTieStart": false,
      "hasTieStop": false,
      "hasSlurStart": false,
      "hasSlurStop": false
    },
    {
      "id": "note_35",
      "index": 35,
      "measureNumber": 13,
      "pitch": "D5",
      "duration": 2,
      "isGrace": false,
      "lyrics": "Lang",
      "hasTieStart": false,
      "hasTieStop": false,
      "hasSlurStart": false,
      "hasSlurStop": false
    },
    {
      "id": "note_36",
      "index": 36,
      "measureNumber": 13,
      "pitch": "D5",
      "duration": 2,
      "isGrace": false,
      "lyrics": "tang",
      "hasTieStart": false,
      "hasTieStop": false,
      "hasSlurStart": false,
      "hasSlurStop": false
    },
    {
      "id": "note_37",
      "index": 37,
      "measureNumber": 14,
      "pitch": "F5",
      "duration": 2,
      "isGrace": false,
      "lyrics": "tính",
      "hasTieStart": false,
      "hasTieStop": false,
      "hasSlurStart": false,
      "hasSlurStop": false
    },
    {
      "id": "note_38",
      "index": 38,
      "measureNumber": 14,
      "pitch": "F5",
      "duration": 2,
      "isGrace": false,
      "lyrics": "lính",
      "hasTieStart": false,
      "hasTieStop": false,
      "hasSlurStart": false,
      "hasSlurStop": false
    },
    {
      "id": "note_39",
      "index": 39,
      "measureNumber": 14,
      "pitch": "D5",
      "duration": 2,
      "isGrace": false,
      "lyrics": "tinh",
      "hasTieStart": false,
      "hasTieStop": false,
      "hasSlurStart": false,
      "hasSlurStop": false
    },
    {
      "id": "note_40",
      "index": 40,
      "measureNumber": 15,
      "pitch": "A4",
      "duration": 2,
      "isGrace": false,
      "lyrics": "tang,",
      "hasTieStart": false,
      "hasTieStop": false,
      "hasSlurStart": false,
      "hasSlurStop": false
    },
    {
      "id": "note_41",
      "index": 41,
      "measureNumber": 15,
      "pitch": "A4",
      "duration": 1,
      "isGrace": false,
      "lyrics": "linh",
      "hasTieStart": false,
      "hasTieStop": false,
      "hasSlurStart": true,
      "hasSlurStop": false
    },
    {
      "id": "note_42",
      "index": 42,
      "measureNumber": 15,
      "pitch": "C5",
      "duration": 1,
      "isGrace": false,
      "lyrics": null,
      "hasTieStart": false,
      "hasTieStop": false,
      "hasSlurStart": false,
      "hasSlurStop": true
    },
    {
      "id": "note_43",
      "index": 43,
      "measureNumber": 15,
      "pitch": "A4",
      "duration": 1,
      "isGrace": false,
      "lyrics": "tính",
      "hasTieStart": false,
      "hasTieStop": false,
      "hasSlurStart": true,
      "hasSlurStop": false
    },
    {
      "id": "note_44",
      "index": 44,
      "measureNumber": 15,
      "pitch": "C5",
      "duration": 1,
      "isGrace": false,
      "lyrics": null,
      "hasTieStart": false,
      "hasTieStop": false,
      "hasSlurStart": false,
      "hasSlurStop": true
    },
    {
      "id": "note_45",
      "index": 45,
      "measureNumber": 16,
      "pitch": "D5",
      "duration": 4,
      "isGrace": false,
      "lyrics": "tang,",
      "hasTieStart": false,
      "hasTieStop": false,
      "hasSlurStart": false,
      "hasSlurStop": false
    },
    {
      "id": "note_46",
      "index": 46,
      "measureNumber": 16,
      "pitch": "D5",
      "duration": 0,
      "isGrace": true,
      "lyrics": null,
      "hasTieStart": false,
      "hasTieStop": false,
      "hasSlurStart": true,
      "hasSlurStop": false
    },
    {
      "id": "note_47",
      "index": 47,
      "measureNumber": 16,
      "pitch": "F5",
      "duration": 2,
      "isGrace": false,
      "lyrics": "giã",
      "hasTieStart": false,
      "hasTieStop": false,
      "hasSlurStart": false,
      "hasSlurStop": true
    },
    {
      "id": "note_48",
      "index": 48,
      "measureNumber": 17,
      "pitch": "A4",
      "duration": 2,
      "isGrace": false,
      "lyrics": "gạo",
      "hasTieStart": false,
      "hasTieStop": false,
      "hasSlurStart": true,
      "hasSlurStop": false
    },
    {
      "id": "note_49",
      "index": 49,
      "measureNumber": 17,
      "pitch": "C5",
      "duration": 2,
      "isGrace": false,
      "lyrics": null,
      "hasTieStart": false,
      "hasTieStop": false,
      "hasSlurStart": false,
      "hasSlurStop": true
    },
    {
      "id": "note_50",
      "index": 50,
      "measureNumber": 17,
      "pitch": "A4",
      "duration": 2,
      "isGrace": false,
      "lyrics": "chày",
      "hasTieStart": false,
      "hasTieStop": false,
      "hasSlurStart": true,
      "hasSlurStop": false
    },
    {
      "id": "note_51",
      "index": 51,
      "measureNumber": 17,
      "pitch": "C5",
      "duration": 2,
      "isGrace": false,
      "lyrics": null,
      "hasTieStart": false,
      "hasTieStop": false,
      "hasSlurStart": false,
      "hasSlurStop": true
    },
    {
      "id": "note_52",
      "index": 52,
      "measureNumber": 18,
      "pitch": "D5",
      "duration": 4,
      "isGrace": false,
      "lyrics": "ba",
      "hasTieStart": false,
      "hasTieStop": false,
      "hasSlurStart": false,
      "hasSlurStop": false
    },
    {
      "id": "note_53",
      "index": 53,
      "measureNumber": 18,
      "pitch": "D5",
      "duration": 2,
      "isGrace": false,
      "lyrics": "quẫy",
      "hasTieStart": false,
      "hasTieStop": false,
      "hasSlurStart": true,
      "hasSlurStop": false
    },
    {
      "id": "note_54",
      "index": 54,
      "measureNumber": 18,
      "pitch": "F5",
      "duration": 2,
      "isGrace": false,
      "lyrics": null,
      "hasTieStart": false,
      "hasTieStop": false,
      "hasSlurStart": false,
      "hasSlurStop": true
    },
    {
      "id": "note_55",
      "index": 55,
      "measureNumber": 19,
      "pitch": "D5",
      "duration": 2,
      "isGrace": false,
      "lyrics": "a",
      "hasTieStart": false,
      "hasTieStop": false,
      "hasSlurStart": true,
      "hasSlurStop": false
    },
    {
      "id": "note_56",
      "index": 56,
      "measureNumber": 19,
      "pitch": "C5",
      "duration": 2,
      "isGrace": false,
      "lyrics": null,
      "hasTieStart": false,
      "hasTieStop": false,
      "hasSlurStart": false,
      "hasSlurStop": true
    },
    {
      "id": "note_57",
      "index": 57,
      "measureNumber": 19,
      "pitch": "A4",
      "duration": 4,
      "isGrace": false,
      "lyrics": "rượng",
      "hasTieStart": false,
      "hasTieStop": false,
      "hasSlurStart": false,
      "hasSlurStop": false
    },
    {
      "id": "note_58",
      "index": 58,
      "measureNumber": 20,
      "pitch": "C5",
      "duration": 4,
      "isGrace": false,
      "lyrics": "a.",
      "hasTieStart": false,
      "hasTieStop": false,
      "hasSlurStart": false,
      "hasSlurStop": false
    }
  ]
}